plastron/stomp/__init__.py
plastron/stomp/daemon.py
plastron/stomp/handlers.py
plastron/stomp/inbox_watcher.py
plastron/stomp/listeners.py
plastron/stomp/commands/__init__.py
plastron/stomp/commands/echo.py
plastron/stomp/commands/export.py
plastron/stomp/commands/importcommand.py
plastron/stomp/commands/publish.py
plastron/stomp/commands/unpublish.py
plastron/stomp/commands/update.py
plastron_stomp-4.6.2.dist-info/METADATA
plastron_stomp-4.6.2.dist-info/WHEEL
plastron_stomp-4.6.2.dist-info/entry_points.txt
plastron_stomp-4.6.2.dist-info/top_level.txt
plastron_stomp-4.6.2.dist-info/RECORD
